[
  {"id": "karp", "name": "Karp", "nameLatin": "Cyprinus carpio", "description": "Ryba słodkowodna z rodziny karpiowatych. Popularny obiekt połowów w Polsce.", "minSize": 30, "closedSeason": "1 stycznia - 30 czerwca (na rzekach)"},
  {"id": "amur", "name": "Amur", "nameLatin": "Ctenopharyngodon idella", "description": "Ryba pochodząca z Azji. Roślinożerca, często spotykany w zbiornikach zaporowych.", "minSize": null, "closedSeason": null},
  {"id": "tolpyga", "name": "Tołpyga", "nameLatin": "Hypophthalmichthys molitrix", "description": "Ryba fitoplanktonożerna. Występuje w zbiornikach zaporowych i jeziorach.", "minSize": null, "closedSeason": null},
  {"id": "leszcz", "name": "Leszcz", "nameLatin": "Abramis brama", "description": "Pospolita ryba karpiowata. Łowiony na metody gruntowe i spławikowe.", "minSize": 25, "closedSeason": null},
  {"id": "ploc", "name": "Płoć", "nameLatin": "Rutilus rutilus", "description": "Jedna z najczęściej łowionych ryb w Polsce. Występuje w niemal każdym zbiorniku.", "minSize": null, "closedSeason": null},
  {"id": "sandacz", "name": "Sandacz", "nameLatin": "Sander lucioperca", "description": "Drapieżnik o delikatnym mięsie. Lubi czystą, przejrzystą wodę.", "minSize": 50, "closedSeason": "1 stycznia - 31 maja"},
  {"id": "szczupak", "name": "Szczupak", "nameLatin": "Esox lucius", "description": "Drapieżnik stawów i jezior. Okres ochronny w czasie tarła.", "minSize": 50, "closedSeason": "1 grudnia - 30 kwietnia (oprócz zbiorników zaporowych)"},
  {"id": "sum", "name": "Sum", "nameLatin": "Silurus glanis", "description": "Największa ryba słodkowodna w Europie. Łowiony na martwą rybkę i przynęty proteinowe.", "minSize": 70, "closedSeason": "1 listopada - 30 czerwca"},
  {"id": "okoń", "name": "Okoń", "nameLatin": "Perca fluviatilis", "description": "Stadna ryba drapieżna. Łowiony na spinning i martwą rybkę.", "minSize": 15, "closedSeason": null},
  {"id": "węgorz", "name": "Węgorz", "nameLatin": "Anguilla anguilla", "description": "Ryba wędrowna, nocny łowca. Wymaga szczególnej ochrony.", "minSize": 40, "closedSeason": null}
]
